{
  "hash": "fb6dff7c",
  "configHash": "dbb28208",
  "lockfileHash": "4512d231",
  "browserHash": "c3e83f5d",
  "optimized": {
    "react": {
      "src": "../../node_modules/react/index.js",
      "file": "react.js",
      "fileHash": "fd115eb8",
      "needsInterop": true
    },
    "react-dom/client": {
      "src": "../../node_modules/react-dom/client.js",
      "file": "react-dom_client.js",
      "fileHash": "4ff9d81e",
      "needsInterop": true
    },
    "react-router-dom": {
      "src": "../../node_modules/react-router-dom/dist/index.js",
      "file": "react-router-dom.js",
      "fileHash": "cfdb6028",
      "needsInterop": false
    },
    "@mui/material": {
      "src": "../../node_modules/@mui/material/index.js",
      "file": "@mui_material.js",
      "fileHash": "97d461a2",
      "needsInterop": false
    },
    "react-icons/io": {
      "src": "../../node_modules/react-icons/io/index.mjs",
      "file": "react-icons_io.js",
      "fileHash": "4c12e450",
      "needsInterop": false
    },
    "react-icons/go": {
      "src": "../../node_modules/react-icons/go/index.mjs",
      "file": "react-icons_go.js",
      "fileHash": "3c833013",
      "needsInterop": false
    },
    "react-icons/fa6": {
      "src": "../../node_modules/react-icons/fa6/index.mjs",
      "file": "react-icons_fa6.js",
      "fileHash": "feeda139",
      "needsInterop": false
    },
    "react-icons/fa": {
      "src": "../../node_modules/react-icons/fa/index.mjs",
      "file": "react-icons_fa.js",
      "fileHash": "7f9af2c4",
      "needsInterop": false
    },
    "react-icons/ri": {
      "src": "../../node_modules/react-icons/ri/index.mjs",
      "file": "react-icons_ri.js",
      "fileHash": "2c388a92",
      "needsInterop": false
    },
    "react-icons/im": {
      "src": "../../node_modules/react-icons/im/index.mjs",
      "file": "react-icons_im.js",
      "fileHash": "b5260c4c",
      "needsInterop": false
    },
    "react-icons/pi": {
      "src": "../../node_modules/react-icons/pi/index.mjs",
      "file": "react-icons_pi.js",
      "fileHash": "b468a09a",
      "needsInterop": false
    },
    "react-icons/hi2": {
      "src": "../../node_modules/react-icons/hi2/index.mjs",
      "file": "react-icons_hi2.js",
      "fileHash": "c8503e90",
      "needsInterop": false
    },
    "react-icons/io5": {
      "src": "../../node_modules/react-icons/io5/index.mjs",
      "file": "react-icons_io5.js",
      "fileHash": "ac76289c",
      "needsInterop": false
    },
    "react-icons/ai": {
      "src": "../../node_modules/react-icons/ai/index.mjs",
      "file": "react-icons_ai.js",
      "fileHash": "b8d8d623",
      "needsInterop": false
    },
    "react-icons/bi": {
      "src": "../../node_modules/react-icons/bi/index.mjs",
      "file": "react-icons_bi.js",
      "fileHash": "41ff190f",
      "needsInterop": false
    }
  },
  "chunks": {
    "chunk-L2Q2RVSC": {
      "file": "chunk-L2Q2RVSC.js"
    },
    "chunk-DJXTQ5DY": {
      "file": "chunk-DJXTQ5DY.js"
    },
    "chunk-DDNM7ENY": {
      "file": "chunk-DDNM7ENY.js"
    }
  }
}